{"config": {"tm_seed": 2021, "car_lights_on": false, "percent_walking": 0, "percent_crossing": 0, "percent_disabled": 0, "max_render_depth_in_meters": 100, "min_visible_vertices_for_render": 4, "num_vehicles": 200, "num_walkers": 30}, "event": [{"timestamp": 0, "info": "Start experiment"}, {"timestamp": 0, "info": "Start experiment"}, {"timestamp": 12.35000018402934, "info": "Collide with Building"}, {"timestamp": 13.350000198930502, "info": "Collide with Building"}, {"timestamp": 14.350000213831663, "info": "Collide with Building"}, {"timestamp": 15.350000228732824, "info": "Collide with Building"}, {"timestamp": 16.350000243633986, "info": "Collide with Building"}, {"timestamp": 17.350000258535147, "info": "Collide with Building"}, {"timestamp": 18.350000273436308, "info": "Collide with Building"}, {"timestamp": 19.35000028833747, "info": "Collide with Building"}, {"timestamp": 20.35000030323863, "info": "Collide with Building"}, {"timestamp": 28.200000420212746, "info": "Goal reached"}], "path_dir": "./unilcd_env/envs/path_points/path_points_t10_32_95.npy", "result": {"success": true, "info": {"timestamp": 28.200000420212746, "info": "Goal reached"}}}