{"config": {"tm_seed": 2021, "car_lights_on": false, "percent_walking": 0, "percent_crossing": 0, "percent_disabled": 0, "max_render_depth_in_meters": 100, "min_visible_vertices_for_render": 4, "num_vehicles": 200, "num_walkers": 30}, "event": [{"timestamp": 0, "info": "Start experiment"}, {"timestamp": 0, "info": "Start experiment"}, {"timestamp": 11.750000175088644, "info": "Collide with Building"}, {"timestamp": 12.750000189989805, "info": "Collide with Building"}, {"timestamp": 13.750000204890966, "info": "Collide with Building"}, {"timestamp": 14.750000219792128, "info": "Collide with Building"}, {"timestamp": 15.750000234693289, "info": "Collide with Building"}, {"timestamp": 16.75000024959445, "info": "Collide with Building"}, {"timestamp": 17.75000026449561, "info": "Collide with Building"}, {"timestamp": 26.00000038743019, "info": "Goal reached"}, {"timestamp": 0, "info": "Start experiment"}, {"timestamp": 16.4500002451241, "info": "Collide with Pedestrian 0010"}, {"timestamp": 25.150000374764204, "info": "Goal reached"}, {"timestamp": 0, "info": "Start experiment"}, {"timestamp": 11.900000177323818, "info": "Collide with Building"}, {"timestamp": 12.90000019222498, "info": "Collide with Building"}, {"timestamp": 13.90000020712614, "info": "Collide with Building"}, {"timestamp": 14.900000222027302, "info": "Collide with Building"}, {"timestamp": 15.900000236928463, "info": "Collide with Building"}, {"timestamp": 16.900000251829624, "info": "Collide with Building"}, {"timestamp": 17.900000266730785, "info": "Collide with Building"}, {"timestamp": 18.900000281631947, "info": "Collide with Building"}, {"timestamp": 27.400000408291817, "info": "Goal reached"}, {"timestamp": 0, "info": "Start experiment"}, {"timestamp": 15.600000232458115, "info": "Collide with Pedestrian 0009"}, {"timestamp": 15.650000233203173, "info": "Collide with Building"}, {"timestamp": 15.650000233203173, "info": "Collide with Pedestrian 0009"}, {"timestamp": 15.650000233203173, "info": "Collide with Building"}, {"timestamp": 0, "info": "Start experiment"}, {"timestamp": 16.650000248104334, "info": "Collide with Building"}, {"timestamp": 17.650000263005495, "info": "Collide with Building"}, {"timestamp": 18.650000277906656, "info": "Collide with Building"}, {"timestamp": 26.850000400096178, "info": "Goal reached"}, {"timestamp": 0, "info": "Start experiment"}, {"timestamp": 26.600000396370888, "info": "Goal reached"}, {"timestamp": 0, "info": "Start experiment"}, {"timestamp": 27.10000040382147, "info": "Goal reached"}, {"timestamp": 0, "info": "Start experiment"}, {"timestamp": 13.40000019967556, "info": "Collide with Pedestrian 0010"}, {"timestamp": 13.450000200420618, "info": "Collide with Building"}, {"timestamp": 13.450000200420618, "info": "Collide with Pedestrian 0010"}, {"timestamp": 14.250000212341547, "info": "Collide with Building"}, {"timestamp": 15.250000227242708, "info": "Collide with Building"}, {"timestamp": 16.25000024214387, "info": "Collide with Building"}, {"timestamp": 17.25000025704503, "info": "Collide with Building"}, {"timestamp": 18.250000271946192, "info": "Collide with Building"}, {"timestamp": 19.250000286847353, "info": "Collide with Building"}, {"timestamp": 28.000000417232513, "info": "Goal reached"}, {"timestamp": 0, "info": "Start experiment"}, {"timestamp": 20.90000031143427, "info": "Collide with Pedestrian 0004"}, {"timestamp": 21.950000327080488, "info": "Collide with Pedestrian 0004"}, {"timestamp": 27.400000408291817, "info": "Goal reached"}, {"timestamp": 0, "info": "Start experiment"}, {"timestamp": 11.750000175088644, "info": "Collide with Building"}, {"timestamp": 12.750000189989805, "info": "Collide with Building"}, {"timestamp": 13.750000204890966, "info": "Collide with Building"}, {"timestamp": 14.750000219792128, "info": "Collide with Building"}, {"timestamp": 15.750000234693289, "info": "Collide with Building"}, {"timestamp": 16.75000024959445, "info": "Collide with Building"}, {"timestamp": 17.75000026449561, "info": "Collide with Building"}, {"timestamp": 18.750000279396772, "info": "Collide with Building"}, {"timestamp": 27.3000004068017, "info": "Goal reached"}, {"timestamp": 0, "info": "Start experiment"}, {"timestamp": 27.400000408291817, "info": "Goal reached"}, {"timestamp": 0, "info": "Start experiment"}, {"timestamp": 28.450000423938036, "info": "Goal reached"}, {"timestamp": 0, "info": "Start experiment"}, {"timestamp": 18.80000028014183, "info": "Collide with Pedestrian 0019"}, {"timestamp": 19.10000028461218, "info": "Collide with Building"}, {"timestamp": 20.10000029951334, "info": "Collide with Building"}, {"timestamp": 21.1000003144145, "info": "Collide with Building"}, {"timestamp": 22.100000329315662, "info": "Collide with Building"}, {"timestamp": 23.100000344216824, "info": "Collide with Building"}, {"timestamp": 24.100000359117985, "info": "Collide with Building"}, {"timestamp": 25.150000374764204, "info": "Collide with Pedestrian 0008"}, {"timestamp": 26.150000389665365, "info": "Collide with Pedestrian 0008"}, {"timestamp": 27.150000404566526, "info": "Collide with Pedestrian 0008"}, {"timestamp": 32.600000485777855, "info": "Goal reached"}, {"timestamp": 0, "info": "Start experiment"}, {"timestamp": 11.750000175088644, "info": "Collide with Building"}, {"timestamp": 12.750000189989805, "info": "Collide with Building"}, {"timestamp": 13.750000204890966, "info": "Collide with Building"}, {"timestamp": 14.750000219792128, "info": "Collide with Building"}, {"timestamp": 15.750000234693289, "info": "Collide with Building"}, {"timestamp": 16.75000024959445, "info": "Collide with Building"}, {"timestamp": 17.75000026449561, "info": "Collide with Building"}, {"timestamp": 18.750000279396772, "info": "Collide with Building"}, {"timestamp": 27.3000004068017, "info": "Goal reached"}, {"timestamp": 0, "info": "Start experiment"}, {"timestamp": 26.850000400096178, "info": "Goal reached"}, {"timestamp": 0, "info": "Start experiment"}, {"timestamp": 19.750000294297934, "info": "Collide with Building"}, {"timestamp": 28.300000421702862, "info": "Goal reached"}, {"timestamp": 0, "info": "Start experiment"}, {"timestamp": 27.200000405311584, "info": "Goal reached"}, {"timestamp": 0, "info": "Start experiment"}, {"timestamp": 28.10000041872263, "info": "Goal reached"}, {"timestamp": 0, "info": "Start experiment"}, {"timestamp": 27.250000406056643, "info": "Goal reached"}, {"timestamp": 0, "info": "Start experiment"}, {"timestamp": 27.35000040754676, "info": "Goal reached"}, {"timestamp": 0, "info": "Start experiment"}, {"timestamp": 12.950000192970037, "info": "Collide with Pedestrian 0007"}, {"timestamp": 13.000000193715096, "info": "Collide with Building"}, {"timestamp": 13.000000193715096, "info": "Collide with Pedestrian 0007"}, {"timestamp": 14.500000216066837, "info": "Collide with Building"}, {"timestamp": 22.100000329315662, "info": "Goal reached"}, {"timestamp": 0, "info": "Start experiment"}, {"timestamp": 15.500000230967999, "info": "Collide with Building"}, {"timestamp": 16.50000024586916, "info": "Collide with Building"}, {"timestamp": 17.50000026077032, "info": "Collide with Building"}, {"timestamp": 18.500000275671482, "info": "Collide with Building"}, {"timestamp": 19.500000290572643, "info": "Collide with Building"}, {"timestamp": 28.000000417232513, "info": "Goal reached"}, {"timestamp": 0, "info": "Start experiment"}, {"timestamp": 23.75000035390258, "info": "Collide with Pedestrian 0018"}, {"timestamp": 28.400000423192978, "info": "Goal reached"}, {"timestamp": 0, "info": "Start experiment"}, {"timestamp": 12.200000181794167, "info": "Collide with Building"}, {"timestamp": 13.200000196695328, "info": "Collide with Building"}, {"timestamp": 14.200000211596489, "info": "Collide with Building"}, {"timestamp": 15.20000022649765, "info": "Collide with Building"}, {"timestamp": 16.20000024139881, "info": "Collide with Building"}, {"timestamp": 17.200000256299973, "info": "Collide with Building"}, {"timestamp": 18.200000271201134, "info": "Collide with Building"}, {"timestamp": 19.200000286102295, "info": "Collide with Building"}, {"timestamp": 27.250000406056643, "info": "Goal reached"}, {"timestamp": 0, "info": "Start experiment"}, {"timestamp": 27.3000004068017, "info": "Goal reached"}, {"timestamp": 0, "info": "Start experiment"}, {"timestamp": 27.3000004068017, "info": "Goal reached"}, {"timestamp": 0, "info": "Start experiment"}, {"timestamp": 2.9000000432133675, "info": "Collide with Pedestrian 0018"}, {"timestamp": 11.750000175088644, "info": "Collide with Building"}, {"timestamp": 12.750000189989805, "info": "Collide with Building"}, {"timestamp": 13.750000204890966, "info": "Collide with Building"}, {"timestamp": 14.750000219792128, "info": "Collide with Building"}, {"timestamp": 15.750000234693289, "info": "Collide with Building"}, {"timestamp": 16.75000024959445, "info": "Collide with Building"}, {"timestamp": 17.75000026449561, "info": "Collide with Building"}, {"timestamp": 18.750000279396772, "info": "Collide with Building"}, {"timestamp": 19.750000294297934, "info": "Collide with Building"}, {"timestamp": 27.750000413507223, "info": "Goal reached"}, {"timestamp": 0, "info": "Start experiment"}, {"timestamp": 27.3000004068017, "info": "Goal reached"}, {"timestamp": 0, "info": "Start experiment"}, {"timestamp": 27.250000406056643, "info": "Goal reached"}, {"timestamp": 0, "info": "Start experiment"}, {"timestamp": 27.400000408291817, "info": "Goal reached"}, {"timestamp": 0, "info": "Start experiment"}, {"timestamp": 27.250000406056643, "info": "Goal reached"}, {"timestamp": 0, "info": "Start experiment"}, {"timestamp": 27.500000409781933, "info": "Goal reached"}, {"timestamp": 0, "info": "Start experiment"}, {"timestamp": 26.900000400841236, "info": "Goal reached"}, {"timestamp": 0, "info": "Start experiment"}, {"timestamp": 26.850000400096178, "info": "Goal reached"}, {"timestamp": 0, "info": "Start experiment"}, {"timestamp": 27.400000408291817, "info": "Goal reached"}, {"timestamp": 0, "info": "Start experiment"}, {"timestamp": 15.20000022649765, "info": "Collide with Pedestrian 0003"}, {"timestamp": 15.250000227242708, "info": "Collide with Building"}, {"timestamp": 15.250000227242708, "info": "Collide with Pedestrian 0003"}, {"timestamp": 15.900000236928463, "info": "Collide with Building"}, {"timestamp": 16.900000251829624, "info": "Collide with Building"}, {"timestamp": 17.900000266730785, "info": "Collide with Building"}, {"timestamp": 18.900000281631947, "info": "Collide with Building"}, {"timestamp": 27.200000405311584, "info": "Goal reached"}, {"timestamp": 0, "info": "Start experiment"}, {"timestamp": 27.05000040307641, "info": "Goal reached"}, {"timestamp": 0, "info": "Start experiment"}, {"timestamp": 27.3000004068017, "info": "Goal reached"}, {"timestamp": 0, "info": "Start experiment"}, {"timestamp": 19.900000296533108, "info": "Collide with Building"}, {"timestamp": 27.700000412762165, "info": "Goal reached"}, {"timestamp": 0, "info": "Start experiment"}, {"timestamp": 27.35000040754676, "info": "Goal reached"}, {"timestamp": 0, "info": "Start experiment"}, {"timestamp": 27.250000406056643, "info": "Goal reached"}, {"timestamp": 0, "info": "Start experiment"}, {"timestamp": 27.200000405311584, "info": "Goal reached"}, {"timestamp": 0, "info": "Start experiment"}, {"timestamp": 27.450000409036875, "info": "Goal reached"}, {"timestamp": 0, "info": "Start experiment"}, {"timestamp": 27.10000040382147, "info": "Goal reached"}, {"timestamp": 0, "info": "Start experiment"}, {"timestamp": 27.200000405311584, "info": "Goal reached"}, {"timestamp": 0, "info": "Start experiment"}, {"timestamp": 27.450000409036875, "info": "Goal reached"}, {"timestamp": 0, "info": "Start experiment"}, {"timestamp": 26.950000401586294, "info": "Goal reached"}, {"timestamp": 0, "info": "Start experiment"}, {"timestamp": 2.8500000424683094, "info": "Collide with Pedestrian 0018"}, {"timestamp": 12.050000179558992, "info": "Collide with Building"}, {"timestamp": 13.050000194460154, "info": "Collide with Building"}, {"timestamp": 14.050000209361315, "info": "Collide with Building"}, {"timestamp": 15.050000224262476, "info": "Collide with Building"}, {"timestamp": 16.050000239163637, "info": "Collide with Building"}, {"timestamp": 17.0500002540648, "info": "Collide with Building"}, {"timestamp": 18.05000026896596, "info": "Collide with Building"}, {"timestamp": 19.05000028386712, "info": "Collide with Building"}, {"timestamp": 27.650000412017107, "info": "Goal reached"}, {"timestamp": 0, "info": "Start experiment"}, {"timestamp": 27.35000040754676, "info": "Goal reached"}, {"timestamp": 0, "info": "Start experiment"}, {"timestamp": 4.400000065565109, "info": "Collide with Pedestrian 0018"}, {"timestamp": 12.050000179558992, "info": "Collide with Building"}, {"timestamp": 13.050000194460154, "info": "Collide with Building"}, {"timestamp": 14.050000209361315, "info": "Collide with Building"}, {"timestamp": 15.050000224262476, "info": "Collide with Building"}, {"timestamp": 16.050000239163637, "info": "Collide with Building"}, {"timestamp": 17.0500002540648, "info": "Collide with Building"}, {"timestamp": 18.05000026896596, "info": "Collide with Building"}, {"timestamp": 19.05000028386712, "info": "Collide with Building"}, {"timestamp": 27.500000409781933, "info": "Goal reached"}, {"timestamp": 0, "info": "Start experiment"}, {"timestamp": 27.200000405311584, "info": "Goal reached"}, {"timestamp": 0, "info": "Start experiment"}, {"timestamp": 26.55000039562583, "info": "Goal reached"}, {"timestamp": 0, "info": "Start experiment"}, {"timestamp": 27.150000404566526, "info": "Goal reached"}, {"timestamp": 0, "info": "Start experiment"}, {"timestamp": 2.7000000402331352, "info": "Collide with Pedestrian 0018"}, {"timestamp": 11.700000174343586, "info": "Collide with Building"}, {"timestamp": 12.700000189244747, "info": "Collide with Building"}, {"timestamp": 13.700000204145908, "info": "Collide with Building"}, {"timestamp": 14.70000021904707, "info": "Collide with Building"}, {"timestamp": 15.70000023394823, "info": "Collide with Building"}, {"timestamp": 16.700000248849392, "info": "Collide with Building"}, {"timestamp": 17.700000263750553, "info": "Collide with Building"}, {"timestamp": 18.700000278651714, "info": "Collide with Building"}, {"timestamp": 27.85000041499734, "info": "Goal reached"}, {"timestamp": 0, "info": "Start experiment"}, {"timestamp": 2.7000000402331352, "info": "Collide with Pedestrian 0018"}, {"timestamp": 7.350000109523535, "info": "Collide with Pedestrian 0021"}, {"timestamp": 11.750000175088644, "info": "Collide with Building"}, {"timestamp": 12.750000189989805, "info": "Collide with Building"}, {"timestamp": 13.750000204890966, "info": "Collide with Building"}, {"timestamp": 14.750000219792128, "info": "Collide with Building"}, {"timestamp": 15.750000234693289, "info": "Collide with Building"}, {"timestamp": 16.75000024959445, "info": "Collide with Building"}, {"timestamp": 17.75000026449561, "info": "Collide with Building"}, {"timestamp": 18.750000279396772, "info": "Collide with Building"}, {"timestamp": 27.150000404566526, "info": "Goal reached"}, {"timestamp": 0, "info": "Start experiment"}, {"timestamp": 19.750000294297934, "info": "Collide with Building"}, {"timestamp": 28.05000041797757, "info": "Goal reached"}, {"timestamp": 0, "info": "Start experiment"}, {"timestamp": 27.200000405311584, "info": "Goal reached"}, {"timestamp": 0, "info": "Start experiment"}, {"timestamp": 27.500000409781933, "info": "Goal reached"}, {"timestamp": 0, "info": "Start experiment"}, {"timestamp": 27.10000040382147, "info": "Goal reached"}, {"timestamp": 0, "info": "Start experiment"}, {"timestamp": 27.000000402331352, "info": "Goal reached"}, {"timestamp": 0, "info": "Start experiment"}, {"timestamp": 27.150000404566526, "info": "Goal reached"}, {"timestamp": 0, "info": "Start experiment"}, {"timestamp": 26.600000396370888, "info": "Goal reached"}, {"timestamp": 0, "info": "Start experiment"}, {"timestamp": 27.450000409036875, "info": "Goal reached"}, {"timestamp": 0, "info": "Start experiment"}, {"timestamp": 27.400000408291817, "info": "Goal reached"}, {"timestamp": 0, "info": "Start experiment"}, {"timestamp": 27.250000406056643, "info": "Goal reached"}, {"timestamp": 0, "info": "Start experiment"}, {"timestamp": 26.400000393390656, "info": "Goal reached"}, {"timestamp": 0, "info": "Start experiment"}, {"timestamp": 27.55000041052699, "info": "Goal reached"}, {"timestamp": 0, "info": "Start experiment"}, {"timestamp": 27.250000406056643, "info": "Goal reached"}, {"timestamp": 0, "info": "Start experiment"}, {"timestamp": 27.000000402331352, "info": "Goal reached"}, {"timestamp": 0, "info": "Start experiment"}, {"timestamp": 27.650000412017107, "info": "Goal reached"}, {"timestamp": 0, "info": "Start experiment"}, {"timestamp": 26.900000400841236, "info": "Goal reached"}, {"timestamp": 0, "info": "Start experiment"}, {"timestamp": 26.850000400096178, "info": "Goal reached"}, {"timestamp": 0, "info": "Start experiment"}, {"timestamp": 27.150000404566526, "info": "Goal reached"}, {"timestamp": 0, "info": "Start experiment"}, {"timestamp": 27.150000404566526, "info": "Goal reached"}, {"timestamp": 0, "info": "Start experiment"}, {"timestamp": 27.35000040754676, "info": "Goal reached"}, {"timestamp": 0, "info": "Start experiment"}, {"timestamp": 27.3000004068017, "info": "Goal reached"}, {"timestamp": 0, "info": "Start experiment"}, {"timestamp": 27.3000004068017, "info": "Goal reached"}, {"timestamp": 0, "info": "Start experiment"}, {"timestamp": 16.25000024214387, "info": "Collide with Pedestrian 0007"}, {"timestamp": 16.650000248104334, "info": "Collide with Building"}, {"timestamp": 0, "info": "Start experiment"}, {"timestamp": 17.650000263005495, "info": "Collide with Building"}, {"timestamp": 18.650000277906656, "info": "Collide with Building"}, {"timestamp": 27.3000004068017, "info": "Goal reached"}, {"timestamp": 0, "info": "Start experiment"}, {"timestamp": 26.600000396370888, "info": "Goal reached"}, {"timestamp": 0, "info": "Start experiment"}, {"timestamp": 27.35000040754676, "info": "Goal reached"}, {"timestamp": 0, "info": "Start experiment"}, {"timestamp": 27.250000406056643, "info": "Goal reached"}, {"timestamp": 0, "info": "Start experiment"}, {"timestamp": 26.850000400096178, "info": "Goal reached"}, {"timestamp": 0, "info": "Start experiment"}, {"timestamp": 19.650000292807817, "info": "Collide with Building"}, {"timestamp": 27.500000409781933, "info": "Goal reached"}, {"timestamp": 0, "info": "Start experiment"}, {"timestamp": 27.05000040307641, "info": "Goal reached"}, {"timestamp": 0, "info": "Start experiment"}, {"timestamp": 27.250000406056643, "info": "Goal reached"}, {"timestamp": 0, "info": "Start experiment"}, {"timestamp": 27.55000041052699, "info": "Goal reached"}, {"timestamp": 0, "info": "Start experiment"}, {"timestamp": 27.400000408291817, "info": "Goal reached"}, {"timestamp": 0, "info": "Start experiment"}, {"timestamp": 26.850000400096178, "info": "Goal reached"}, {"timestamp": 0, "info": "Start experiment"}, {"timestamp": 26.850000400096178, "info": "Goal reached"}, {"timestamp": 0, "info": "Start experiment"}, {"timestamp": 27.500000409781933, "info": "Goal reached"}, {"timestamp": 0, "info": "Start experiment"}, {"timestamp": 26.850000400096178, "info": "Goal reached"}, {"timestamp": 0, "info": "Start experiment"}, {"timestamp": 26.750000398606062, "info": "Goal reached"}, {"timestamp": 0, "info": "Start experiment"}, {"timestamp": 26.950000401586294, "info": "Goal reached"}, {"timestamp": 0, "info": "Start experiment"}, {"timestamp": 27.150000404566526, "info": "Goal reached"}, {"timestamp": 0, "info": "Start experiment"}, {"timestamp": 21.500000320374966, "info": "Collide with Pedestrian 0017"}, {"timestamp": 26.400000393390656, "info": "Goal reached"}, {"timestamp": 0, "info": "Start experiment"}, {"timestamp": 11.750000175088644, "info": "Collide with Building"}, {"timestamp": 12.750000189989805, "info": "Collide with Building"}, {"timestamp": 13.750000204890966, "info": "Collide with Building"}, {"timestamp": 14.750000219792128, "info": "Collide with Building"}, {"timestamp": 15.750000234693289, "info": "Collide with Building"}, {"timestamp": 16.75000024959445, "info": "Collide with Building"}, {"timestamp": 17.75000026449561, "info": "Collide with Building"}, {"timestamp": 18.750000279396772, "info": "Collide with Building"}, {"timestamp": 27.000000402331352, "info": "Goal reached"}, {"timestamp": 0, "info": "Start experiment"}, {"timestamp": 27.150000404566526, "info": "Goal reached"}, {"timestamp": 0, "info": "Start experiment"}, {"timestamp": 27.05000040307641, "info": "Goal reached"}, {"timestamp": 0, "info": "Start experiment"}, {"timestamp": 27.10000040382147, "info": "Goal reached"}, {"timestamp": 0, "info": "Start experiment"}, {"timestamp": 27.150000404566526, "info": "Goal reached"}, {"timestamp": 0, "info": "Start experiment"}, {"timestamp": 27.3000004068017, "info": "Goal reached"}, {"timestamp": 0, "info": "Start experiment"}, {"timestamp": 19.750000294297934, "info": "Collide with Building"}, {"timestamp": 27.80000041425228, "info": "Goal reached"}, {"timestamp": 0, "info": "Start experiment"}, {"timestamp": 26.50000039488077, "info": "Goal reached"}, {"timestamp": 0, "info": "Start experiment"}, {"timestamp": 26.900000400841236, "info": "Goal reached"}, {"timestamp": 0, "info": "Start experiment"}, {"timestamp": 27.35000040754676, "info": "Goal reached"}, {"timestamp": 0, "info": "Start experiment"}, {"timestamp": 27.35000040754676, "info": "Goal reached"}, {"timestamp": 0, "info": "Start experiment"}, {"timestamp": 27.450000409036875, "info": "Goal reached"}, {"timestamp": 0, "info": "Start experiment"}, {"timestamp": 27.150000404566526, "info": "Goal reached"}, {"timestamp": 0, "info": "Start experiment"}, {"timestamp": 26.700000397861004, "info": "Goal reached"}, {"timestamp": 0, "info": "Start experiment"}, {"timestamp": 27.10000040382147, "info": "Goal reached"}, {"timestamp": 0, "info": "Start experiment"}, {"timestamp": 27.35000040754676, "info": "Goal reached"}, {"timestamp": 0, "info": "Start experiment"}, {"timestamp": 27.10000040382147, "info": "Goal reached"}, {"timestamp": 0, "info": "Start experiment"}, {"timestamp": 27.700000412762165, "info": "Goal reached"}, {"timestamp": 0, "info": "Start experiment"}, {"timestamp": 27.35000040754676, "info": "Goal reached"}, {"timestamp": 0, "info": "Start experiment"}, {"timestamp": 27.250000406056643, "info": "Goal reached"}, {"timestamp": 0, "info": "Start experiment"}, {"timestamp": 27.05000040307641, "info": "Goal reached"}, {"timestamp": 0, "info": "Start experiment"}, {"timestamp": 27.05000040307641, "info": "Goal reached"}, {"timestamp": 0, "info": "Start experiment"}, {"timestamp": 26.750000398606062, "info": "Goal reached"}, {"timestamp": 0, "info": "Start experiment"}, {"timestamp": 27.400000408291817, "info": "Goal reached"}, {"timestamp": 0, "info": "Start experiment"}, {"timestamp": 26.850000400096178, "info": "Goal reached"}, {"timestamp": 0, "info": "Start experiment"}, {"timestamp": 27.250000406056643, "info": "Goal reached"}, {"timestamp": 0, "info": "Start experiment"}, {"timestamp": 27.150000404566526, "info": "Goal reached"}, {"timestamp": 0, "info": "Start experiment"}, {"timestamp": 26.400000393390656, "info": "Goal reached"}, {"timestamp": 0, "info": "Start experiment"}, {"timestamp": 26.950000401586294, "info": "Goal reached"}, {"timestamp": 0, "info": "Start experiment"}, {"timestamp": 27.05000040307641, "info": "Goal reached"}, {"timestamp": 0, "info": "Start experiment"}, {"timestamp": 27.3000004068017, "info": "Goal reached"}, {"timestamp": 0, "info": "Start experiment"}, {"timestamp": 27.10000040382147, "info": "Goal reached"}, {"timestamp": 0, "info": "Start experiment"}, {"timestamp": 27.10000040382147, "info": "Goal reached"}, {"timestamp": 0, "info": "Start experiment"}, {"timestamp": 27.60000041127205, "info": "Goal reached"}, {"timestamp": 0, "info": "Start experiment"}, {"timestamp": 27.400000408291817, "info": "Goal reached"}, {"timestamp": 0, "info": "Start experiment"}, {"timestamp": 27.500000409781933, "info": "Goal reached"}, {"timestamp": 0, "info": "Start experiment"}, {"timestamp": 26.600000396370888, "info": "Goal reached"}, {"timestamp": 0, "info": "Start experiment"}, {"timestamp": 26.950000401586294, "info": "Goal reached"}, {"timestamp": 0, "info": "Start experiment"}, {"timestamp": 27.500000409781933, "info": "Goal reached"}, {"timestamp": 0, "info": "Start experiment"}, {"timestamp": 27.60000041127205, "info": "Goal reached"}, {"timestamp": 0, "info": "Start experiment"}, {"timestamp": 27.3000004068017, "info": "Goal reached"}, {"timestamp": 0, "info": "Start experiment"}, {"timestamp": 27.250000406056643, "info": "Goal reached"}, {"timestamp": 0, "info": "Start experiment"}, {"timestamp": 27.200000405311584, "info": "Goal reached"}, {"timestamp": 0, "info": "Start experiment"}, {"timestamp": 27.05000040307641, "info": "Goal reached"}, {"timestamp": 0, "info": "Start experiment"}, {"timestamp": 27.400000408291817, "info": "Goal reached"}, {"timestamp": 0, "info": "Start experiment"}, {"timestamp": 27.200000405311584, "info": "Goal reached"}, {"timestamp": 0, "info": "Start experiment"}, {"timestamp": 26.850000400096178, "info": "Goal reached"}, {"timestamp": 0, "info": "Start experiment"}, {"timestamp": 27.950000416487455, "info": "Goal reached"}, {"timestamp": 0, "info": "Start experiment"}, {"timestamp": 27.200000405311584, "info": "Goal reached"}, {"timestamp": 0, "info": "Start experiment"}, {"timestamp": 27.10000040382147, "info": "Goal reached"}, {"timestamp": 0, "info": "Start experiment"}, {"timestamp": 27.650000412017107, "info": "Goal reached"}, {"timestamp": 0, "info": "Start experiment"}, {"timestamp": 27.3000004068017, "info": "Goal reached"}, {"timestamp": 0, "info": "Start experiment"}, {"timestamp": 27.3000004068017, "info": "Goal reached"}, {"timestamp": 0, "info": "Start experiment"}, {"timestamp": 26.55000039562583, "info": "Goal reached"}, {"timestamp": 0, "info": "Start experiment"}, {"timestamp": 26.700000397861004, "info": "Goal reached"}, {"timestamp": 0, "info": "Start experiment"}, {"timestamp": 27.250000406056643, "info": "Goal reached"}, {"timestamp": 0, "info": "Start experiment"}, {"timestamp": 28.05000041797757, "info": "Goal reached"}, {"timestamp": 0, "info": "Start experiment"}, {"timestamp": 26.850000400096178, "info": "Goal reached"}, {"timestamp": 0, "info": "Start experiment"}, {"timestamp": 27.10000040382147, "info": "Goal reached"}, {"timestamp": 0, "info": "Start experiment"}, {"timestamp": 27.150000404566526, "info": "Goal reached"}, {"timestamp": 0, "info": "Start experiment"}, {"timestamp": 26.900000400841236, "info": "Goal reached"}, {"timestamp": 0, "info": "Start experiment"}, {"timestamp": 28.650000426918268, "info": "Goal reached"}, {"timestamp": 0, "info": "Start experiment"}, {"timestamp": 26.700000397861004, "info": "Goal reached"}, {"timestamp": 0, "info": "Start experiment"}, {"timestamp": 27.85000041499734, "info": "Goal reached"}, {"timestamp": 0, "info": "Start experiment"}, {"timestamp": 27.10000040382147, "info": "Goal reached"}, {"timestamp": 0, "info": "Start experiment"}, {"timestamp": 27.250000406056643, "info": "Goal reached"}, {"timestamp": 0, "info": "Start experiment"}, {"timestamp": 27.3000004068017, "info": "Goal reached"}, {"timestamp": 0, "info": "Start experiment"}, {"timestamp": 26.600000396370888, "info": "Goal reached"}, {"timestamp": 0, "info": "Start experiment"}, {"timestamp": 27.450000409036875, "info": "Goal reached"}, {"timestamp": 0, "info": "Start experiment"}, {"timestamp": 27.05000040307641, "info": "Goal reached"}, {"timestamp": 0, "info": "Start experiment"}, {"timestamp": 27.250000406056643, "info": "Goal reached"}, {"timestamp": 0, "info": "Start experiment"}, {"timestamp": 27.3000004068017, "info": "Goal reached"}, {"timestamp": 0, "info": "Start experiment"}, {"timestamp": 27.3000004068017, "info": "Goal reached"}, {"timestamp": 0, "info": "Start experiment"}, {"timestamp": 27.05000040307641, "info": "Goal reached"}, {"timestamp": 0, "info": "Start experiment"}, {"timestamp": 27.500000409781933, "info": "Goal reached"}, {"timestamp": 0, "info": "Start experiment"}, {"timestamp": 27.200000405311584, "info": "Goal reached"}, {"timestamp": 0, "info": "Start experiment"}, {"timestamp": 27.05000040307641, "info": "Goal reached"}, {"timestamp": 0, "info": "Start experiment"}, {"timestamp": 27.05000040307641, "info": "Goal reached"}, {"timestamp": 0, "info": "Start experiment"}, {"timestamp": 27.35000040754676, "info": "Goal reached"}, {"timestamp": 0, "info": "Start experiment"}, {"timestamp": 27.400000408291817, "info": "Goal reached"}, {"timestamp": 0, "info": "Start experiment"}, {"timestamp": 27.10000040382147, "info": "Goal reached"}, {"timestamp": 0, "info": "Start experiment"}, {"timestamp": 27.150000404566526, "info": "Goal reached"}, {"timestamp": 0, "info": "Start experiment"}, {"timestamp": 26.950000401586294, "info": "Goal reached"}, {"timestamp": 0, "info": "Start experiment"}, {"timestamp": 27.200000405311584, "info": "Goal reached"}, {"timestamp": 0, "info": "Start experiment"}, {"timestamp": 27.200000405311584, "info": "Goal reached"}, {"timestamp": 0, "info": "Start experiment"}, {"timestamp": 27.05000040307641, "info": "Goal reached"}, {"timestamp": 0, "info": "Start experiment"}, {"timestamp": 27.000000402331352, "info": "Goal reached"}, {"timestamp": 0, "info": "Start experiment"}, {"timestamp": 27.35000040754676, "info": "Goal reached"}, {"timestamp": 0, "info": "Start experiment"}, {"timestamp": 27.400000408291817, "info": "Goal reached"}, {"timestamp": 0, "info": "Start experiment"}, {"timestamp": 27.05000040307641, "info": "Goal reached"}, {"timestamp": 0, "info": "Start experiment"}, {"timestamp": 27.400000408291817, "info": "Goal reached"}, {"timestamp": 0, "info": "Start experiment"}, {"timestamp": 27.150000404566526, "info": "Goal reached"}, {"timestamp": 0, "info": "Start experiment"}, {"timestamp": 27.250000406056643, "info": "Goal reached"}, {"timestamp": 0, "info": "Start experiment"}, {"timestamp": 27.10000040382147, "info": "Goal reached"}, {"timestamp": 0, "info": "Start experiment"}, {"timestamp": 27.05000040307641, "info": "Goal reached"}, {"timestamp": 0, "info": "Start experiment"}, {"timestamp": 26.30000039190054, "info": "Goal reached"}, {"timestamp": 0, "info": "Start experiment"}, {"timestamp": 27.950000416487455, "info": "Goal reached"}, {"timestamp": 0, "info": "Start experiment"}, {"timestamp": 27.10000040382147, "info": "Goal reached"}, {"timestamp": 0, "info": "Start experiment"}, {"timestamp": 27.3000004068017, "info": "Goal reached"}, {"timestamp": 0, "info": "Start experiment"}, {"timestamp": 26.950000401586294, "info": "Goal reached"}, {"timestamp": 0, "info": "Start experiment"}, {"timestamp": 26.50000039488077, "info": "Goal reached"}, {"timestamp": 0, "info": "Start experiment"}, {"timestamp": 25.700000382959843, "info": "Goal reached"}, {"timestamp": 0, "info": "Start experiment"}, {"timestamp": 27.000000402331352, "info": "Goal reached"}, {"timestamp": 0, "info": "Start experiment"}, {"timestamp": 27.150000404566526, "info": "Goal reached"}, {"timestamp": 0, "info": "Start experiment"}, {"timestamp": 27.150000404566526, "info": "Goal reached"}, {"timestamp": 0, "info": "Start experiment"}, {"timestamp": 27.10000040382147, "info": "Goal reached"}, {"timestamp": 0, "info": "Start experiment"}, {"timestamp": 27.3000004068017, "info": "Goal reached"}, {"timestamp": 0, "info": "Start experiment"}, {"timestamp": 27.05000040307641, "info": "Goal reached"}, {"timestamp": 0, "info": "Start experiment"}, {"timestamp": 27.3000004068017, "info": "Goal reached"}, {"timestamp": 0, "info": "Start experiment"}, {"timestamp": 26.650000397115946, "info": "Goal reached"}, {"timestamp": 0, "info": "Start experiment"}, {"timestamp": 27.35000040754676, "info": "Goal reached"}, {"timestamp": 0, "info": "Start experiment"}, {"timestamp": 27.150000404566526, "info": "Goal reached"}, {"timestamp": 0, "info": "Start experiment"}, {"timestamp": 26.850000400096178, "info": "Goal reached"}, {"timestamp": 0, "info": "Start experiment"}, {"timestamp": 27.150000404566526, "info": "Goal reached"}, {"timestamp": 0, "info": "Start experiment"}, {"timestamp": 26.900000400841236, "info": "Goal reached"}, {"timestamp": 0, "info": "Start experiment"}, {"timestamp": 26.850000400096178, "info": "Goal reached"}, {"timestamp": 0, "info": "Start experiment"}, {"timestamp": 27.35000040754676, "info": "Goal reached"}, {"timestamp": 0, "info": "Start experiment"}, {"timestamp": 26.900000400841236, "info": "Goal reached"}, {"timestamp": 0, "info": "Start experiment"}, {"timestamp": 27.400000408291817, "info": "Goal reached"}, {"timestamp": 0, "info": "Start experiment"}, {"timestamp": 27.05000040307641, "info": "Goal reached"}, {"timestamp": 0, "info": "Start experiment"}, {"timestamp": 27.200000405311584, "info": "Goal reached"}, {"timestamp": 0, "info": "Start experiment"}, {"timestamp": 27.10000040382147, "info": "Goal reached"}, {"timestamp": 0, "info": "Start experiment"}, {"timestamp": 27.05000040307641, "info": "Goal reached"}, {"timestamp": 0, "info": "Start experiment"}, {"timestamp": 27.35000040754676, "info": "Goal reached"}, {"timestamp": 0, "info": "Start experiment"}, {"timestamp": 27.200000405311584, "info": "Goal reached"}, {"timestamp": 0, "info": "Start experiment"}, {"timestamp": 27.10000040382147, "info": "Goal reached"}, {"timestamp": 0, "info": "Start experiment"}, {"timestamp": 27.200000405311584, "info": "Goal reached"}, {"timestamp": 0, "info": "Start experiment"}, {"timestamp": 27.000000402331352, "info": "Goal reached"}, {"timestamp": 0, "info": "Start experiment"}, {"timestamp": 26.900000400841236, "info": "Goal reached"}, {"timestamp": 0, "info": "Start experiment"}, {"timestamp": 27.10000040382147, "info": "Goal reached"}, {"timestamp": 0, "info": "Start experiment"}, {"timestamp": 27.05000040307641, "info": "Goal reached"}, {"timestamp": 0, "info": "Start experiment"}, {"timestamp": 27.450000409036875, "info": "Goal reached"}, {"timestamp": 0, "info": "Start experiment"}, {"timestamp": 27.05000040307641, "info": "Goal reached"}, {"timestamp": 0, "info": "Start experiment"}, {"timestamp": 27.10000040382147, "info": "Goal reached"}, {"timestamp": 0, "info": "Start experiment"}, {"timestamp": 26.950000401586294, "info": "Goal reached"}, {"timestamp": 0, "info": "Start experiment"}, {"timestamp": 27.200000405311584, "info": "Goal reached"}, {"timestamp": 0, "info": "Start experiment"}, {"timestamp": 27.250000406056643, "info": "Goal reached"}, {"timestamp": 0, "info": "Start experiment"}, {"timestamp": 26.950000401586294, "info": "Goal reached"}, {"timestamp": 0, "info": "Start experiment"}, {"timestamp": 27.200000405311584, "info": "Goal reached"}], "path_dir": "./unilcd_env/envs/path_points/path_points_t10_32_95.npy", "result": {"success": true, "info": {"timestamp": 27.200000405311584, "info": "Goal reached"}}}